pytest_twisted/__init__.py
pytest_twisted/three.py
pytest_twisted/two.py
pytest_twisted-1.14.3.dist-info/LICENSE
pytest_twisted-1.14.3.dist-info/METADATA
pytest_twisted-1.14.3.dist-info/WHEEL
pytest_twisted-1.14.3.dist-info/entry_points.txt
pytest_twisted-1.14.3.dist-info/top_level.txt
pytest_twisted-1.14.3.dist-info/RECORD
