Metadata-Version: 2.1
Name: pytest-twisted
Version: 1.14.3
Summary: A twisted plugin for pytest.
Home-page: https://github.com/pytest-dev/pytest-twisted
Author: Ralf Schmitt, Kyle Altendorf, Victor Titor
Author-email: sda@fstab.net
Classifier: Development Status :: 5 - Production/Stable
Classifier: Intended Audience :: Developers
Classifier: License :: OSI Approved :: BSD License
Classifier: Operating System :: OS Independent
Classifier: Programming Language :: Python
Classifier: Topic :: Software Development :: Testing
Classifier: Programming Language :: Python :: 2
Classifier: Programming Language :: Python :: 2.7
Classifier: Programming Language :: Python :: 3
Classifier: Programming Language :: Python :: 3.6
Classifier: Programming Language :: Python :: 3.7
Classifier: Programming Language :: Python :: 3.8
Classifier: Programming Language :: Python :: 3.9
Classifier: Programming Language :: Python :: 3.10
Classifier: Programming Language :: Python :: 3.11
Classifier: Programming Language :: Python :: 3.12
Classifier: Programming Language :: Python :: Implementation :: CPython
Classifier: Programming Language :: Python :: Implementation :: PyPy
Requires-Python: >=2.7,!=3.0.*,!=3.1.*,!=3.2.*,!=3.3.*,!=3.4.*,!=3.5.*
License-File: LICENSE
Requires-Dist: greenlet
Requires-Dist: pytest>=2.3
Requires-Dist: decorator
Provides-Extra: dev
Requires-Dist: pre-commit; extra == "dev"
Requires-Dist: black; extra == "dev"
Provides-Extra: pyside2
Requires-Dist: qt5reactor[pyside2]>=0.6.3; extra == "pyside2"
Provides-Extra: pyqt5
Requires-Dist: qt5reactor[pyqt5]>=0.6.2; extra == "pyqt5"
